binary_to_text/__init__.py
binary_to_text/main.py
binary_to_text-0.0.4.dist-info/METADATA
binary_to_text-0.0.4.dist-info/WHEEL
binary_to_text-0.0.4.dist-info/licenses/LICENSE
binary_to_text-0.0.4.dist-info/RECORD
