Metadata-Version: 2.3
Name: binary_to_text
Version: 0.0.4
Summary: Binary to text and Text to binary
Author: Muka
License-File: LICENSE
Classifier: License :: OSI Approved :: MIT License
Classifier: Operating System :: OS Independent
Classifier: Programming Language :: Python :: 3
Requires-Python: >=3.10.0
